MANIFEST.in
README.rst
setup.py
docs/HISTORY.txt
docs/INSTALL.txt
docs/LICENSE.GPL
docs/LICENSE.txt
redturtle/__init__.py
redturtle.deletepolicy.egg-info/PKG-INFO
redturtle.deletepolicy.egg-info/SOURCES.txt
redturtle.deletepolicy.egg-info/dependency_links.txt
redturtle.deletepolicy.egg-info/entry_points.txt
redturtle.deletepolicy.egg-info/namespace_packages.txt
redturtle.deletepolicy.egg-info/not-zip-safe
redturtle.deletepolicy.egg-info/requires.txt
redturtle.deletepolicy.egg-info/top_level.txt
redturtle/deletepolicy/__init__.py
redturtle/deletepolicy/config.py
redturtle/deletepolicy/configure.zcml
redturtle/deletepolicy/patches.py
redturtle/deletepolicy/tests.py
redturtle/deletepolicy/profiles/default/actions.xml
redturtle/deletepolicy/profiles/default/metadata.xml
redturtle/deletepolicy/profiles/default/skins.xml
redturtle/deletepolicy/skins/redturtle.deletepolicy/folder_cut.cpy
redturtle/deletepolicy/skins/redturtle.deletepolicy/folder_cut.cpy.metadata
redturtle/deletepolicy/skins/redturtle.deletepolicy/folder_delete.cpy
redturtle/deletepolicy/skins/redturtle.deletepolicy/folder_delete.cpy.metadata