Metadata-Version: 1.1
Name: redturtle.deletepolicy
Version: 2.1.1
Summary: Modified policy for deleting objects in Plone
Home-page: http://plone.org/products/redturtle.deletepolicy
Author: RedTurtle Technology
Author-email: sviluppoplone@redturtle.it
License: GPL
Keywords: delete policy permissions security
Platform: UNKNOWN
Classifier: Framework :: Plone
Classifier: Framework :: Plone :: 4.1
Classifier: Framework :: Plone :: 4.2
Classifier: Framework :: Plone :: 4.3
Classifier: Programming Language :: Python
Classifier: Topic :: Software Development :: Libraries :: Python Modules
